ab_nic_sw/ab_nic_fpga.py
ab_nic_sw/change_port.py
ab_nic_sw/compare_pcap.py
ab_nic_sw/eth_interface_rate.py
ab_nic_sw/hbm_packet_controller.py
ab_nic_sw/pcap_to_hbm.py
ab_nic_sw/ptp.py
ab_nic_sw/status_display.py
ab_nic_sw-0.2.1.dist-info/entry_points.txt
ab_nic_sw-0.2.1.dist-info/LICENSE
ab_nic_sw-0.2.1.dist-info/WHEEL
ab_nic_sw-0.2.1.dist-info/METADATA
ab_nic_sw-0.2.1.dist-info/RECORD
