Metadata-Version: 2.1
Name: ab-nic-sw
Version: 0.2.1
Summary: Alveo Burst NIC Control Software
License: CSIRO Open Source Software Licence
Author: Andrew Bolin, Jason van Aardt, CSIRO
Requires-Python: >=3.7,<4.0
Classifier: License :: Other/Proprietary License
Classifier: Programming Language :: Python :: 3
Classifier: Programming Language :: Python :: 3.10
Classifier: Programming Language :: Python :: 3.7
Classifier: Programming Language :: Python :: 3.8
Classifier: Programming Language :: Python :: 3.9
Requires-Dist: dpkt (>=1.9.7,<2.0.0)
Requires-Dist: fxpmath (>=0.4.5,<0.5.0)
Requires-Dist: rich (>=12.0.1,<13.0.0)
Requires-Dist: scapy (>=2.4.5,<3.0.0)
Requires-Dist: ska-low-cbf-fpga (>=0.12.0,<0.13.0)
